transcribe_zh_en/__init__.py
transcribe_zh_en/audio_to_text.py
transcribe_zh_en/main.py
transcribe_zh_en_p1/__init__.py
transcribe_zh_en_p1/audio_to_text.py
transcribe_zh_en_p1/main.py
transcribe_zh_en_p1-0.1.2.dist-info/LICENSE
transcribe_zh_en_p1-0.1.2.dist-info/METADATA
transcribe_zh_en_p1-0.1.2.dist-info/WHEEL
transcribe_zh_en_p1-0.1.2.dist-info/entry_points.txt
transcribe_zh_en_p1-0.1.2.dist-info/top_level.txt
transcribe_zh_en_p1-0.1.2.dist-info/RECORD
