Metadata-Version: 2.1
Name: transcribe-zh-en-p1
Version: 0.1.2
Summary: This package is a part of a larger pipeline. This is package (PART:1). A package to convert Video containing spoken Chinese audio and Chinese written text and convert it into spoken English and English written text.
Home-page: https://github.com/Abdulhamid97Mousa/transcribe_zh_en_p1
Author: Mousa Abdulhamid
Author-email: mousa.abdulhamid97@gmail.com
License: UNKNOWN
Platform: UNKNOWN
Classifier: Programming Language :: Python :: 3
Classifier: License :: OSI Approved :: MIT License
Classifier: Operating System :: OS Independent
Requires-Python: >=3.8, <3.9
Requires-Dist: demucs (==4.0.1)
Requires-Dist: dill (==0.3.4)
Requires-Dist: ffmpeg-python (==0.2.0)
Requires-Dist: fsspec (==2024.9.0)
Requires-Dist: multiprocess (==0.70.12.2)
Requires-Dist: numpy (==1.23.5)
Requires-Dist: opencv-python (==4.6.0.66)
Requires-Dist: paddlepaddle-gpu (==2.5.1)
Requires-Dist: paddlespeech (==1.4.2)
Requires-Dist: torch (==2.4.1)
Requires-Dist: typeguard (==2.13.3)
Requires-Dist: urllib3 (<=2.0.0)
